docopt_plus
