Metadata-Version: 1.1
Name: docopt-plus
Version: 0.6.3a1
Summary: Pythonic argument parser, that will make you smile
Home-page: https://github.com/frnhr/docopt_plus
Author: Fran Hrženjak
Author-email: fran.hrzenjak@gmail.com
License: MIT
Keywords: option arguments parsing optparse argparse getopt
Platform: UNKNOWN
Classifier: Development Status :: 3 - Alpha
Classifier: Topic :: Utilities
Classifier: Programming Language :: Python :: 2.5
Classifier: Programming Language :: Python :: 2.6
Classifier: Programming Language :: Python :: 2.7
Classifier: Programming Language :: Python :: 3.2
Classifier: Programming Language :: Python :: 3.3
Classifier: License :: OSI Approved :: MIT License
